exoclasma_index/__init__.py
exoclasma_index/config.json
exoclasma_index/exoclasma_index.py
exoclasma_index-0.9.5.dist-info/METADATA
exoclasma_index-0.9.5.dist-info/WHEEL
exoclasma_index-0.9.5.dist-info/entry_points.txt
exoclasma_index-0.9.5.dist-info/licenses/LICENSE
exoclasma_index-0.9.5.dist-info/RECORD
