Metadata-Version: 2.1
Name: exoclasma-index
Version: 0.9.5
Summary: Reference Sequence and Capture Intervals Preparation for ExoClasma Suite
Project-URL: Homepage, https://github.com/regnveig/exoclasma-index
Project-URL: Bug Tracker, https://github.com/regnveig/exoclasma-index/issues
Author-email: Emil Viesná <regnveig@yandex.ru>, Minja Fishman <minja-f@yandex.ru>
Keywords: bed,bioinformatics,fasta,indexing,restrictase
Classifier: Development Status :: 3 - Alpha
Classifier: Environment :: Console
Classifier: Intended Audience :: Science/Research
Classifier: License :: OSI Approved :: GNU General Public License v3 (GPLv3)
Classifier: Natural Language :: English
Classifier: Operating System :: POSIX :: Linux
Classifier: Programming Language :: Python :: 3.6
Classifier: Programming Language :: Python :: 3.7
Classifier: Programming Language :: Python :: 3.8
Classifier: Programming Language :: Python :: 3.9
Classifier: Programming Language :: Python :: 3.10
Classifier: Topic :: Scientific/Engineering :: Bio-Informatics
Requires-Python: >=3.6
Requires-Dist: biopython>=1.76
Requires-Dist: pandas>=1.0.3
